{
  "战斗菜单": {
    "Name": "战斗菜单",
    "MainSize": [1280, 720],
    "Offset": [1160, 175],
    "Size": [70, 60],
    "Type": "Static",
    "Image": "战斗菜单.png"
  },
  "AP不足": {
    "Name": "AP不足",
    "MainSize": [1280, 720],
    "Offset": [540, 36],
    "Size": [200, 60],
    "Type": "Static",
    "Image": "AP不足.png"
  },
  "金苹果": {
    "Name": "金苹果",
    "MainSize": [1280, 720],
    "Offset": [330, 270],
    "Size": [600, 100],
    "Type": "Static"
  },
  "银苹果": {
    "Name": "银苹果",
    "MainSize": [1280, 720],
    "Offset": [330, 420],
    "Size": [600, 100],
    "Type": "Static"
  },
  "银苹果不足": {
    "Name": "银苹果不足",
    "MainSize": [1280, 720],
    "Offset": [330, 420],
    "Size": [640, 50],
    "Type": "Static",
    "Image": "银苹果不足.png"
  },
  "队伍确认": {
    "Name": "队伍确认",
    "MainSize": [1280, 720],
    "Offset": [1040, 0],
    "Size": [240, 80],
    "Type": "Static",
    "Image": "队伍确认.png"
  },
  "助战选择": {
    "Name": "助战选择",
    "MainSize": [1280, 720],
    "Offset": [1040, 0],
    "Size": [240, 80],
    "Type": "Static",
    "Image": "助战选择.png"
  },
  "开始任务": {
    "Name": "开始任务",
    "MainSize": [1280, 720],
    "Offset": [1122, 650],
    "Size": [130, 50],
    "Type": "Static"
  },
  "加载提示": {
    "Name": "加载提示",
    "MainSize": [1280, 720],
    "Offset": [500, 150],
    "Size": [300, 100],
    "Type": "Static",
    "Image": "加载提示.png"
  },
  "战斗轮次": {
    "Name": "战斗轮次",
    "MainSize": [1280, 720],
    "Offset": [850, 10],
    "Size": [100, 30],
    "Type": "Static"
  },
  "剩余敌人": {
    "Name": "剩余敌人",
    "MainSize": [1280, 720],
    "Offset": [850, 46],
    "Size": [130, 30],
    "Type": "Static"
  },
  "回合数": {
    "Name": "回合数",
    "MainSize": [1280, 720],
    "Offset": [850, 82],
    "Size": [130, 30],
    "Type": "Static"
  },
  "Attack": {
    "Name": "Attack",
    "MainSize": [1280, 720],
    "Offset": [1070, 540],
    "Size": [130, 130],
    "Type": "Static"
  },
  "战斗速度": {
    "Name": "战斗速度",
    "MainSize": [1280, 720],
    "Offset": [1086, 76],
    "Size": [98, 24],
    "Type": "Static",
    "Image": "战斗速度.png"
  },
  "Buster": {
    "Name": "Buster",
    "MainSize": [1280, 720],
    "Size": [184, 81],
    "Type": "Dynamic",
    "Image": "Buster.png"
  },
  "Arts": {
    "Name": "Arts",
    "MainSize": [1280, 720],
    "Size": [146, 81],
    "Type": "Dynamic",
    "Image": "Arts.png"
  },
  "Quick": {
    "Name": "Quick",
    "MainSize": [1280, 720],
    "Size": [172, 89],
    "Type": "Dynamic",
    "Image": "Quick.png"
  },
  "宝具背景1": {
    "Name": "宝具背景1",
    "MainSize": [1280, 720],
    "Offset": [340, 120],
    "Size": [140, 180],
    "Type": "Static"
  },
  "宝具背景2": {
    "Name": "宝具背景2",
    "MainSize": [1280, 720],
    "Offset": [570, 120],
    "Size": [140, 180],
    "Type": "Static"
  },
  "宝具背景3": {
    "Name": "宝具背景3",
    "MainSize": [1280, 720],
    "Offset": [800, 120],
    "Size": [140, 180],
    "Type": "Static"
  },
  "礼装满破": {
    "Name": "礼装满破",
    "MainSize": [1280, 720],
    "Size": [8, 7],
    "Type": "Dynamic",
    "Image": "Star-center.png",
    "MaxDiff": 0.02
  },
  "克制": {
    "Name": "克制",
    "MainSize": [1280, 720],
    "Size": [47, 49],
    "Type": "Dynamic",
    "Image": "克制.png",
    "MaxDiff": 0.1
  },
  "抵抗": {
    "Name": "抵抗",
    "MainSize": [1280, 720],
    "Size": [45, 50],
    "Type": "Dynamic",
    "Image": "抵抗.png",
    "MaxDiff": 0.1
  },
  "滚动条-上": {
    "Name": "滚动条-上",
    "MainSize": [1280, 720],
    "Offset": [16, 0],
    "Size": [32, 20],
    "Type": "Anchor",
    "Image": "滚动条-上.png"
  },
  "滚动条-下": {
    "Name": "滚动条-下",
    "MainSize": [1280, 720],
    "Offset": [16, 20],
    "Size": [32, 20],
    "Type": "Anchor",
    "Image": "滚动条-下.png"
  },
  "滚动条范围": {
    "Name": "滚动条范围",
    "MainSize": [1280, 720],
    "Offset": [1224, 174],
    "Size": [32, 518],
    "Type": "Static"
  },
  "羁绊-左": {
    "Name": "羁绊-左",
    "MainSize": [1280, 720],
    "Offset": [80, 168],
    "Size": [100, 36],
    "Type": "Static",
    "Image": "羁绊-左.png"
  },
  "点击画面": {
    "Name": "点击画面",
    "MainSize": [1280, 720],
    "Offset": [300, 600],
    "Size": [700, 100],
    "Type": "Static"
  },
  "获得经验": {
    "Name": "获得经验",
    "MainSize": [1280, 720],
    "Offset": [650, 186],
    "Size": [180, 36],
    "Type": "Static",
    "Image": "获得经验.png"
  },
  "获得物品": {
    "Name": "获得物品",
    "MainSize": [1280, 720],
    "Offset": [114, 73],
    "Size": [100, 36],
    "Type": "Static",
    "Image": "获得物品.png"
  },
  "助战从者定位": {
    "Name": "最后登录",
    "MainSize": [1280, 720],
    "Offset": [-778, -18],
    "Size": [98, 38],
    "SearchArea": [[820, 195], [130, 375]],
    "Type": "MultiDynamic",
    "Image": "最后登录.png"
  },
  "助战从者-名称": {
    "Name": "助战选择-从者-名称",
    "MainSize": [1280, 720],
    "Offset": [310, 90],
    "Size": [450, 38],
    "Type": "Anchor"
  },
  "助战从者-宝具": {
    "Name": "助战选择-从者-宝具",
    "MainSize": [1280, 720],
    "Offset": [310, 126],
    "Size": [450, 38],
    "Type": "Anchor"
  },
  "助战从者-礼装": {
    "Name": "助战选择-从者-礼装",
    "MainSize": [1280, 720],
    "Offset": [3, 133],
    "Size": [160, 50],
    "Type": "Anchor"
  },
  "助战从者-等级": {
    "Name": "助战选择-从者-等级",
    "MainSize": [1280, 720],
    "Offset": [50, 10],
    "Size": [110, 30],
    "Type": "Anchor"
  },
  "助战从者-职阶": {
    "Name": "助战选择-从者-职阶",
    "MainSize": [1280, 720],
    "Offset": [-2, 0],
    "Size": [50, 50],
    "Type": "Anchor"
  },
  "助战从者-技能1": {
    "Name": "助战选择-从者-技能1",
    "MainSize": [1280, 720],
    "Offset": [792, 149],
    "Size": [30, 20],
    "Type": "Anchor"
  },
  "助战从者-技能2": {
    "Name": "助战选择-从者-技能2",
    "MainSize": [1280, 720],
    "Offset": [872, 149],
    "Size": [30, 20],
    "Type": "Anchor"
  },
  "助战从者-技能3": {
    "Name": "助战选择-从者-技能3",
    "MainSize": [1280, 720],
    "Offset": [952, 149],
    "Size": [30, 20],
    "Type": "Anchor"
  },
  "关卡1": {
    "Name": "关卡1",
    "MainSize": [1280, 720],
    "Offset": [660, 140],
    "Size": [200, 100],
    "Type": "Static"
  },
  "羁绊加深": {
    "Name": "羁绊加深",
    "MainSize": [1280, 720],
    "Offset": [660, 323],
    "Size": [160, 40],
    "Type": "Static",
    "Image": "羁绊加深.png"
  },
  "助战-职阶选择": {
    "Name": "助战-职阶选择",
    "MainSize": [1280, 720],
    "Size": [40, 40],
    "Positions": [
      [72, 108],
      [139, 108],
      [207, 108],
      [274, 108],
      [342, 108],
      [409, 108],
      [477, 108],
      [544, 108],
      [612, 108]
    ],
    "Names": ["全部", "剑", "弓", "枪", "骑", "术", "杀", "狂", "特殊"],
    "Type": "MultiStatic"
  },
  "战斗-敌人位置": {
    "Name": "战斗-敌人位置",
    "MainSize": [1280, 720],
    "Positions": [[8, 0], [249, 0], [488, 0]],
    "ClickOffset": [10, 10],
    "ClickSize": [200, 50],
    "Type": "MultiStatic"
  },
  "战斗-从者位置": {
    "Name": "战斗-从者位置",
    "MainSize": [1280, 720],
    "Positions": [[16, 380], [333, 380], [653, 380]],
    "Type": "MultiStatic"
  },
  "战斗-御主技能": {
    "Name": "战斗-御主技能",
    "MainSize": [1280, 720],
    "Positions": [[880, 286], [968, 286], [1056, 286]],
    "Type": "MultiStatic"
  },
  "从者技能-剩余": {
    "Name": "从者技能-剩余",
    "MainSize": [1280, 720],
    "Positions": [[14, 218], [108, 218], [201, 218]],
    "Size": [18, 18],
    "Type": "Static",
    "Image": "从者技能-剩余.png"
  },
  "从者职阶-文字": {
    "Name": "从者职阶-文字",
    "MainSize": [1280, 720],
    "Offset": [4, 316],
    "Size": [90, 18],
    "Type": "Static"
  },
  "从者HP": {
    "Name": "从者HP",
    "MainSize": [1280, 720],
    "Offset": [160, 239],
    "Size": [120, 20],
    "Type": "Static"
  },
  "从者NP": {
    "Name": "从者NP",
    "MainSize": [1280, 720],
    "Offset": [160, 275],
    "Size": [120, 20],
    "Type": "Static"
  },
  "Cards": {
    "Name": "从者NP",
    "MainSize": [1280, 720],
    "Positions": [
      [35, 355],
      [290, 355],
      [545, 355],
      [805, 355],
      [1065, 355]
    ],
    "Size": [200, 270],
    "ClickOffset": [30, 65],
    "ClickSize": [130, 160],
    "Type": "MultiStatic"
  },
  "右侧空白区域": {
    "Name": "右侧空白区域",
    "MainSize": [1280, 720],
    "Offset": [1240, 230],
    "Size": [40, 50],
    "Type": "Static"
  },
  "与从者的羁绊": {
    "Name": "与从者的羁绊",
    "MainSize": [1280, 720],
    "Offset": [80, 168],
    "Size": [100, 36],
    "Type": "Static",
    "Image": "羁绊-左.png"
  },
  "下一步": {
    "Name": "下一步",
    "MainSize": [1280, 720],
    "Offset": [1010, 650],
    "Size": [200, 50],
    "Type": "Static"
  },
  "助战更新": {
    "Name": "助战更新",
    "MainSize": [1280, 720],
    "Offset": [790, 105],
    "Size": [90, 50],
    "Type": "Static",
    "Image": "助战更新.png"
  },
  "助战-确认更新": {
    "Name": "助战-确认更新",
    "MainSize": [1280, 720],
    "Offset": [740, 540],
    "Size": [190, 50],
    "Type": "Static",
    "Image": "助战-确认更新.png"
  },
  "角色1技能1": {
    "Name": "角色1技能1",
    "MainSize": [1280, 720],
    "Offset": [38, 546],
    "Size": [64, 64],
    "Type": "Static"
  },
  "角色1技能2": {
    "Name": "角色1技能2",
    "MainSize": [1280, 720],
    "Offset": [132, 546],
    "Size": [64, 64],
    "Type": "Static"
  },
  "角色1技能3": {
    "Name": "角色1技能3",
    "MainSize": [1280, 720],
    "Offset": [226, 546],
    "Size": [64, 64],
    "Type": "Static"
  },
  "角色2技能1": {
    "Name": "角色2技能1",
    "MainSize": [1280, 720],
    "Offset": [356, 546],
    "Size": [64, 64],
    "Type": "Static"
  },
  "角色2技能2": {
    "Name": "角色2技能2",
    "MainSize": [1280, 720],
    "Offset": [450, 546],
    "Size": [64, 64],
    "Type": "Static"
  },
  "角色2技能3": {
    "Name": "角色2技能3",
    "MainSize": [1280, 720],
    "Offset": [544, 546],
    "Size": [64, 64],
    "Type": "Static"
  },
  "角色3技能1": {
    "Name": "角色3技能1",
    "MainSize": [1280, 720],
    "Offset": [674, 546],
    "Size": [64, 64],
    "Type": "Static"
  },
  "角色3技能2": {
    "Name": "角色3技能2",
    "MainSize": [1280, 720],
    "Offset": [768, 546],
    "Size": [64, 64],
    "Type": "Static"
  },
  "角色3技能3": {
    "Name": "角色3技能3",
    "MainSize": [1280, 720],
    "Offset": [862, 546],
    "Size": [64, 64],
    "Type": "Static"
  },
  "御主技能1": {
    "Name": "御主技能1",
    "MainSize": [1280, 720],
    "Offset": [874, 280],
    "Size": [64, 64],
    "Type": "Static"
  },
  "御主技能2": {
    "Name": "御主技能2",
    "MainSize": [1280, 720],
    "Offset": [963, 280],
    "Size": [64, 64],
    "Type": "Static"
  },
  "御主技能3": {
    "Name": "御主技能3",
    "MainSize": [1280, 720],
    "Offset": [1052, 280],
    "Size": [64, 64],
    "Type": "Static"
  },
  "目标1-3": {
    "Name": "目标1-3",
    "MainSize": [1280, 720],
    "Offset": [220, 320],
    "Size": [200, 200],
    "Type": "Static"
  },
  "目标2-3": {
    "Name": "目标2-3",
    "MainSize": [1280, 720],
    "Offset": [540, 320],
    "Size": [200, 200],
    "Type": "Static"
  },
  "目标3-3": {
    "Name": "目标3-3",
    "MainSize": [1280, 720],
    "Offset": [860, 320],
    "Size": [200, 200],
    "Type": "Static"
  },
  "目标1-4": {
    "Name": "目标1-4",
    "MainSize": [1280, 720],
    "Offset": [60, 270],
    "Size": [150, 150],
    "Type": "Static"
  },
  "目标2-4": {
    "Name": "目标2-4",
    "MainSize": [1280, 720],
    "Offset": [260, 270],
    "Size": [150, 150],
    "Type": "Static"
  },
  "目标3-4": {
    "Name": "目标3-4",
    "MainSize": [1280, 720],
    "Offset": [460, 270],
    "Size": [150, 150],
    "Type": "Static"
  },
  "目标4-4": {
    "Name": "目标4-4",
    "MainSize": [1280, 720],
    "Offset": [660, 270],
    "Size": [150, 150],
    "Type": "Static"
  },
  "目标5-4": {
    "Name": "目标5-4",
    "MainSize": [1280, 720],
    "Offset": [860, 270],
    "Size": [150, 150],
    "Type": "Static"
  },
  "目标6-4": {
    "Name": "目标6-4",
    "MainSize": [1280, 720],
    "Offset": [1060, 270],
    "Size": [150, 150],
    "Type": "Static"
  },
  "申请好友": {
    "Name": "申请好友",
    "MainSize": [1280, 720],
    "Offset": [850, 585],
    "Size": [200, 60],
    "Type": "Static",
    "Image": "申请.png"
  },
  "关闭": {
    "Name": "关闭",
    "MainSize": [1280, 720],
    "Offset": [540, 540],
    "Size": [200, 45],
    "Type": "Static",
    "Image": "关闭.png"
  },
  "补充AP-决定": {
    "Name": "补充AP-决定",
    "MainSize": [1280, 720],
    "Offset": [740, 540],
    "Size": [200, 50],
    "Type": "Static",
    "Image": "决定.png"
  },
  "AP不足-关闭": {
    "Name": "AP不足-关闭",
    "MainSize": [1280, 720],
    "Offset": [550, 595],
    "Size": [180, 50],
    "Type": "Static",
    "Image": "AP不足-关闭.png"
  },
  "右下-菜单": {
    "Name": "右下-菜单",
    "MainSize": [1280, 720],
    "Offset": [1130, 670],
    "Size": [110, 40],
    "Type": "Static",
    "Image": "右下-菜单.png"
  },
  "御主技能": {
    "Name": "御主技能",
    "MainSize": [1280, 720],
    "Offset": [1164, 286],
    "Size": [60, 60],
    "Type": "Static",
    "Image": "御主技能.png"
  },
  "左上-关闭": {
    "Name": "左上-关闭",
    "MainSize": [1280, 720],
    "Offset": [80, 28],
    "Size": [60, 30],
    "Type": "Static",
    "Image": "左上-关闭.png"
  },
  "请点击画面": {
    "Name": "请点击画面",
    "MainSize": [1280, 720],
    "ClickOffset": [-500, -600],
    "ClickSize": [600, 600],
    "Offset": [540, 622],
    "Size": [200, 50],
    "Type": "Static",
    "Image": "请点击画面.png"
  },
  "万华镜奶光": {
    "Name": "万华镜奶光",
    "MainSize": [1280, 720],
    "ClickSize": [500, 140],
    "Size": [150, 140],
    "Type": "Dynamic",
    "Image": "万华镜奶光.png"
  },
  "从者1-NP": {
    "Name": "从者1-NP",
    "MainSize": [1280, 720],
    "Offset": [220, 654],
    "Size": [80, 22],
    "Type": "Static"
  },
  "从者2-NP": {
    "Name": "从者2-NP",
    "MainSize": [1280, 720],
    "Offset": [539, 654],
    "Size": [80, 22],
    "Type": "Static"
  },
  "从者3-NP": {
    "Name": "从者3-NP",
    "MainSize": [1280, 720],
    "Offset": [858, 654],
    "Size": [80, 22],
    "Type": "Static"
  }
}