{
  "Name": "手动",
  "Strategy": {},
  "Scenes": {
    "关卡选择": {
      "Name": "关卡选择",
      "Condition": true,
      "Actions": [
        {"Type": "InnerCall", "Target": "manual"},
        {"Type": "Wait", "Time": 1}
      ],
      "Next": ["助战选择", "AP不足", "关卡选择"]
    },
    "获得物品": {
      "Name": "获得物品",
      "Condition": ["获得物品"],
      "Actions": [
        {"Type": "InnerCall", "Target": "save_screen"},
        {"Type": "Click", "Target": "下一步"},
        {"Type": "Wait", "Time": 1}
      ],
      "Next": ["获得物品", "关卡选择", "申请好友"]
    },
    "助战选择": {
      "Name": "助战选择",
      "Condition": ["助战选择"],
      "Actions": [
        {"Type": "InnerCall", "Target": "manual"},
        {"Type": "Wait", "Time": 1}
      ],
      "Next": ["助战选择", "队伍确认"]
    },
    "选择技能": {
      "Name": "选择技能",
      "Condition": ["战斗菜单"],
      "Actions": [
        {"Type": "InnerCall", "Target": "manual"},
        {"Type": "Wait", "Time": 1}
      ],
      "Next": ["选择技能", "选择指令卡"]
    },
    "选择指令卡": {
      "Name": "选择指令卡",
      "Condition": ["战斗速度"],
      "Actions": [
        {"Type": "InnerCall", "Target": "manual"},
        {"Type": "Wait", "Time": 1}
      ],
      "Next": ["选择指令卡", "选择技能", "获得羁绊"]
    }
  },
  "Resources": {}
}